aws_recommendations/__init__.py
aws_recommendations/cost_estimations.py
aws_recommendations/ebs.py
aws_recommendations/ec2.py
aws_recommendations/elb.py
aws_recommendations/rds.py
aws_recommendations/recommendation.py
aws_recommendations/redshift.py
aws_recommendations/s3.py
aws_recommendations/truted_advisor.py
aws_recommendations/utils.py
aws_recommendations-0.0.10.dist-info/LICENCE
aws_recommendations-0.0.10.dist-info/METADATA
aws_recommendations-0.0.10.dist-info/WHEEL
aws_recommendations-0.0.10.dist-info/top_level.txt
aws_recommendations-0.0.10.dist-info/RECORD
